{
  "title": {
    "en": "Workday",
    "sv": "Arbetsdag"
  },
  "titleFormatted": {
    "en": "Is workday ([[include_bridge_day]] bridge days)",
    "sv": "Är arbetsdag ([[include_bridge_day]] klämdagar)"
  },
  "hint": {
    "en": "True on weekdays that are not Swedish public holidays.",
    "sv": "Sant på vardagar som inte är svenska helgdagar."
  },
  "args": [
    {
      "name": "include_bridge_day",
      "type": "dropdown",
      "required": false,
      "value": "true",
      "title": {
        "en": "Bridge days",
        "sv": "Klämdagar"
      },
      "values": [
        { "id": "true", "title": { "en": "Including", "sv": "Inkludera" } },
        { "id": "false", "title": { "en": "Excluding", "sv": "Exkludera" } }
      ]
    }
  ]
}
